elasticwrap/EsWrapper.py
elasticwrap/__init__.py
elasticwrap/parser/ESLexer.py
elasticwrap/parser/ESListener.py
elasticwrap/parser/ESParser.py
elasticwrap/parser/__init__.py
elasticwrap-0.0.6.dist-info/LICENSE
elasticwrap-0.0.6.dist-info/METADATA
elasticwrap-0.0.6.dist-info/WHEEL
elasticwrap-0.0.6.dist-info/top_level.txt
elasticwrap-0.0.6.dist-info/RECORD
