Metadata-Version: 2.1
Name: elasticwrap
Version: 0.0.6
Summary: Wrapper to use mutiple versions of Elasticsearch
Home-page: UNKNOWN
Author: Angelica Garcia
Author-email: agalejo@amarello.com.mx
License: UNKNOWN
Platform: UNKNOWN
Classifier: Programming Language :: Python :: 3
Classifier: License :: OSI Approved :: MIT License
Classifier: Operating System :: OS Independent
Requires-Python: >=3.6
